{
  "source_pdf": "dataset/12/biology/biology12/lebo112.pdf",
  "grade": "12",
  "subject": "Biology",
  "doc_type": "chapter",
  "chapter": "12",
  "book": "lebo112.pdf",
  "pages": [
    {
      "page": 1,
      "text": "An ecosystem can be visualised as a functional unit of\nnature, where living organisms interact among themselves\nand also with the surrounding physical environment.\nEcosystem varies greatly in size from a small pond to a\nlarge forest or a sea. Many ecologists regard the entire\nbiosphere as a global ecosystem, as a composite of all\nlocal ecosystems on Earth. Since this system is too much\nbig and complex to be studied at one time, it is convenient\nto divide it into two basic categories, namely terrestrial\nand aquatic. Forest, grassland and desert are some\nexamples of terrestrial ecosystems; pond, lake, wetland,\nriver and estuary are some examples of aquatic\necosystems. Crop fields and an aquarium may also be\nconsidered as man-made ecosystems.\nWe will first look at the structure of the ecosystem, in\norder to appreciate the input (productivity), transfer of\nenergy (food chain/web, nutrient cycling) and the output\n(degradation and energy loss). We will also look at the\nrelationships – cycles, chains, webs – that are created as\na result of these energy flows within the system and their\ninter- relationship.\nCHAPTER 12\nECOSYSTEM\n12.1 Ecosystem–Structure\nand Function\n12.2. Productivity\n12.3 Decomposition\n12.4 Energy Flow\n12.5 Ecological Pyramids"
    },
    {
      "page": 2,
      "text": "206\nBIOLOGY\n12.1 ECOSYSTEM – STRUCTURE AND FUNCTION\nIn earlier classes, you have looked at the various components of the\nenvironment- abiotic and biotic. You studied how the individual biotic\nand abiotic factors affected each other and their surrounding. Let us look\nat these components in a more integrated manner and see how the flow of\nenergy takes place within these components of the ecosystem.\nInteraction of biotic and abiotic components result in a physical\nstructure that is characteristic for each type of ecosystem. Identification\nand enumeration of plant and animal species of an ecosystem gives its\nspecies composition. Vertical distribution of different species occupying\ndifferent levels is called stratification. For example, trees occupy top\nvertical strata or layer of a forest, shrubs the second and herbs and grasses\noccupy the bottom layers.\nThe components of the ecosystem are seen to function as a unit when\nyou consider the following aspects:\n(i) Productivity;\n(ii) Decomposition;\n(iii) Energy flow; and\n(iv) Nutrient cycling.\nTo understand the ethos of an aquatic ecosystem let us take a small\npond as an example. This is fairly a self-sustainable unit and rather simple\nexample that explain even the complex interactions that exist in an aquatic\necosystem. A pond is a shallow water body in which all the above\nmentioned four basic components of an ecosystem are well exhibited.\nThe abiotic component is the water with all the dissolved inorganic and\norganic substances and the rich soil deposit at the bottom of the pond.\nThe solar input, the cycle of temperature, day-length and other climatic\nconditions regulate the rate of function of the entire pond. The autotrophic\ncomponents include the phytoplankton, some algae and the floating,\nsubmerged and marginal plants found at the edges. The consumers are\nrepresented by the zooplankton, the free swimming and bottom dwelling\nforms. The decomposers are the fungi, bacteria and flagellates especially\nabundant in the bottom of the pond. This system performs all the functions\nof any ecosystem and of the biosphere as a whole, i.e., conversion of\ninorganic into organic material with the help of the radiant energy of the\nsun by the autotrophs; consumption of the autotrophs by heterotrophs;\ndecomposition and mineralisation of the dead matter to release them back\nfor reuse by the autotrophs, these event are repeated over and over again.\nThere is unidirectional movement of energy towards the higher trophic\nlevels and its dissipation and loss as heat to the environment.\n12.2 PRODUCTIVITY\nA constant input of solar energy is the basic requirement for any ecosystem\nto function and sustain. Primary production is defined as the amount of"
    },
    {
      "page": 3,
      "text": "207\nECOSYSTEM\nbiomass or organic matter produced per unit area over a time period by\nplants during photosynthesis. It is expressed in terms of weight (gm–2) or\nenergy (kcal m–2). The rate of biomass production is called productivity.\nIt is expressed in terms of gm–2 yr –1 or (kcal m–2) yr–1 to compare the\nproductivity of different ecosystems. It can be divided into gross primary\nproductivity (GPP) and net primary productivity (NPP). Gross primary\nproductivity of an ecosystem is the rate of production of organic matter\nduring photosynthesis. A considerable amount of GPP is utilised by plants\nin respiration. Gross primary productivity minus respiration losses (R),\nis the net primary productivity (NPP).\nGPP – R = NPP\nNet primary productivity is the available biomass for the consumption\nto heterotrophs (herbiviores and decomposers). Secondary productivity\nis defined as the rate of formation of new organic matter by\nconsumers.\nPrimary productivity depends on the plant species inhabiting a\nparticular area. It also depends on a variety of environmental factors,\navailability of nutrients and photosynthetic capacity of plants. Therefore,\nit varies in different types of ecosystems. The annual net primary\nproductivity of the whole biosphere is approximately 170 billion tons\n(dry weight) of organic matter. Of this, despite occupying about 70 per\ncent of the surface, the productivity of the oceans are only 55 billion tons.\nRest of course, is on land. Discuss the main reason for the low\nproductivity of ocean with your teacher.\n12.3 DECOMPOSITION\nYou may have heard of the earthworm being referred to as the farmer’s\n‘friend’. This is so because they help in the breakdown of complex organic\nmatter as well as in loosening of the soil. Similarly,  decomposers break\ndown complex organic matter into inorganic substances like carbon\ndioxide, water and nutrients and the process is called decomposition.\nDead plant remains such as leaves, bark, flowers and dead remains of\nanimals, including fecal matter, constitute detritus, which is the raw\nmaterial for decomposition. The important steps in the process of\ndecomposition are fragmentation, leaching, catabolism, humification and\nmineralisation.\nDetritivores (e.g., earthworm) break down detritus into smaller particles.\nThis process is called fragmentation. By the process of leaching, water-\nsoluble inorganic nutrients go down into the soil horizon and get precipitated\nas unavailable salts. Bacterial and fungal enzymes degrade detritus into\nsimpler inorganic substances. This process is called as catabolism.\nIt is important to note that all the above steps in decomposition  operate\nsimultaneously on the detritus (Figure 12.1). Humification and\nmineralisation occur during decomposition in the soil. Humification leads"
    },
    {
      "page": 4,
      "text": "208\nBIOLOGY\nto accumulation of a dark coloured amorphous substance called humus\nthat is highly resistant to microbial action and undergoes decomposition\nat an extremely slow rate. Being colloidal in nature it serves as a reservoir\nof nutrients. The humus is further degraded by some microbes and release\nof inorganic nutrients occur by the process  known as mineralisation.\nDecomposition is largely an oxygen-requiring process. The rate of\ndecomposition is controlled by chemical composition of detritus and\nclimatic factors. In a particular climatic condition, decomposition rate\nis slower if detritus is rich in lignin and chitin, and quicker, if detritus is\nrich in nitrogen and water-soluble substances like sugars. Temperature\nand soil moisture are the most important climatic factors that regulate\ndecomposition through their effects on the activities of soil microbes.\nWarm and moist environment favour decomposition whereas low\ntemperature and anaerobiosis inhibit decomposition resulting in build\nup of organic materials.\nFigure 12.1 Diagrammatic representation of decomposition cycle in a terrestrial ecosystem"
    },
    {
      "page": 5,
      "text": "209\nECOSYSTEM\n12.4 ENERGY FLOW\nExcept for the deep sea hydro-thermal ecosystem, sun is the only source\nof energy for all ecosystems on Earth.  Of the incident solar radiation less\nthan 50 per cent of it is photosynthetically active radiation (PAR).  We\nknow that plants and photosynthetic bacteria (autotrophs), fix Sun’s\nradiant energy to make food from simple inorganic materials. Plants\ncapture only 2-10  per cent of the PAR and this small amount of energy\nsustains the entire living world.  So, it is very important to know how the\nsolar energy captured by plants flows through different organisms of an\necosystem. All organisms are dependent for their food on producers, either\ndirectly or indirectly. So you find unidirectional flow of energy from the\nsun to producers and then to consumers. Is this in keeping with the first\nlaw of thermodynamics?\nFurther, ecosystems are not exempt from the Second Law of\nthermodynamics. They need a constant supply of energy to synthesise\nthe molecules they require, to counteract the universal tendency toward\nincreasing disorderliness.\nThe green plant in the ecosystem are called producers. In a terrestrial\necosystem, major producers are herbaceous and woody plants. Likewise,\nproducers in an aquatic ecosystem are various species like phytoplankton,\nalgae and higher plants.\nYou have read about the food chains and webs that exist in nature.\nStarting from the plants (or producers) food chains or rather webs are\nformed such that an animal feeds on a plant or on another animal and in\nturn is food for another. The chain or web is formed because of this\ninterdependency. No energy that is trapped into an organism remains in\nit for ever. The energy trapped by the producer, hence, is either passed on\nto a consumer or the organism dies. Death of organism is the beginning\nof the detritus food chain/web.\nAll animals depend on plants (directly or indirectly) for their food needs.\nThey are hence called consumers and also heterotrophs.  If they feed on\nthe producers, the plants, they are called primary consumers, and if the\nanimals eat other animals which in turn eat the plants (or their produce)\nthey are called secondary consumers. Likewise, you could have tertiary\nconsumers too.  Obviously the primary consumers will be herbivores.\nSome common herbivores are insects, birds and mammals in terrestrial\necosystem and molluscs in aquatic ecosystem.\nThe consumers that feed on these herbivores are carnivores, or more\ncorrectly primary carnivores (though secondary consumers). Those\nanimals that depend on the primary carnivores for food are labelled\nsecondary carnivores. A simple grazing food chain (GFC) is depicted\nbelow:\n \nGrass                            Goat                               Man\n   (Producer)                 (Primary Consumer)\n(Secondary consumer)"
    },
    {
      "page": 6,
      "text": "210\nBIOLOGY\nThe detritus food chain (DFC) begins with dead organic matter. It is\nmade up of decomposers which are heterotrophic organisms, mainly\nfungi and bacteria. They meet their energy and nutrient requirements by\ndegrading dead organic matter or detritus. These are also known as\nsaprotrophs (sapro: to decompose). Decomposers secrete digestive\nenzymes that breakdown dead and waste materials into simple, inorganic\nmaterials, which are subsequently absorbed by them.\nIn an aquatic ecosystem, GFC is the major conduit for energy flow.\nAs against this, in a terrestrial ecosystem, a much larger fraction of energy\nflows through the detritus food chain than through the GFC. Detritus\nfood chain may be connected with the grazing food chain at some levels:\nsome of the organisms of DFC are prey to the GFC animals, and in a natural\necosystem, some animals like cockroaches, crows, etc., are omnivores.\nThese natural interconnection of food chains make it a  food web. How\nwould you classify human beings!\nOrganisms occupy a place in the natural surroundings or in a\ncommunity according to their feeding relationship with other organisms.\nBased on the source of their nutrition or food, organisms occupy a specific\nplace in the food chain that is known as their trophic level. Producers\nbelong to the first trophic level, herbivores (primary consumer) to the\nsecond and carnivores (secondary consumer) to the third (Figure 12.2).\nFigure 12.2 Diagrammatic representation of trophic levels in an ecosystem\n210"
    },
    {
      "page": 7,
      "text": "211\nECOSYSTEM\nFigure 12.3 Energy flow through different trophic levels\n211\nThe important point to note is that the amount of energy decreases at\nsuccessive trophic levels.  When any organism dies it is converted to\ndetritus or dead biomass that serves as an energy source for decomposers.\nOrganisms at each trophic level depend on those at the lower trophic level\nfor their energy demands.\nEach trophic level has a certain mass of living material at a particular\ntime called as the standing crop. The standing crop is measured as the\nmass of living organisms (biomass) or the number in a unit area. The\nbiomass of a species is expressed in terms of fresh or dry weight.\nMeasurement of biomass in terms of dry weight is more accurate. Why?\nThe number of trophic levels in the grazing food chain is restricted as\nthe transfer of energy follows 10 per cent law – only 10 per cent of the\nenergy is transferred to each trophic level from the lower trophic level.  In\nnature, it is possible to have so many levels – producer, herbivore, primary\ncarnivore, secondary carnivore in the grazing food chain (Figure 12.3) .\nDo you think there is any such limitation in a detritus food chain?\n12.5 ECOLOGICAL PYRAMIDS\nYou must be familiar with the shape of a pyramid. The base of a pyramid\nis broad and it narrows towards the apex. One gets a similar shape,\nwhether you express the food or energy relationship between organisms"
    },
    {
      "page": 8,
      "text": "212\nBIOLOGY\nat different trophic levels. This, relationship is expressed in terms of\nnumber, biomass or energy. The base of each pyramid represents the\nproducers or the first trophic level while the apex represents tertiary or\ntop level consumer. The three types of ecological pyramids that are usually\nstudied are (a) pyramid of number; (b) pyramid of biomass and (c) pyramid\nof energy. For detail (see Figure 12.4 a, b, c and d).\nFigure 12.4 (a) Pyramid of numbers in a grassland ecosystem. Only three top-carnivores are\nsupported in an ecosystem based on production of nearly 6 millions plants\nFigure 12.4 (b) Pyramid of biomass shows a sharp decrease in biomass at higher trophic levels\nFigure 12.4 (c) Inverted pyramid of biomass-small standing crop of phytoplankton supports large\nstanding crop of zooplankton"
    },
    {
      "page": 9,
      "text": "213\nECOSYSTEM\nFigure 12.4 (d) An ideal pyramid of energy. Observe that primary producers convert only 1% of\n  the energy in the sunlight available to them into NPP\nAny calculations of energy content, biomass or numbers, has to include\nall organisms at that trophic level.  No generalisations we make will be\ntrue if we take only a few individuals at any trophic level into account.\nAlso a given organism may occupy more than one trophic level\nsimultaneously. One must remember that the trophic level represents a\nfunctional level, not a species as such. A given species may occupy more\nthan one trophic level in the same ecosystem at the same time; for example,\na sparrow is a primary consumer when it eats seeds, fruits, peas, and a\nsecondary consumer when it eats insects and worms. Can you work out\nhow many trophic levels human beings function at in a food chain?\nIn most ecosystems, all the pyramids, of number, of energy and\nbiomass are upright, i.e., producers are more in number and biomass\nthan the herbivores, and herbivores are more in number and biomass\nthan the carnivores.  Also energy at a lower trophic level is always more\nthan at a higher level.\nThere are exceptions to this generalisation: If you were to count the\nnumber of insects feeding on a big tree what kind of pyramid would you\nget?  Now add an estimate of the number of small birds depending on the\ninsects, as also the number of larger birds eating the smaller. Draw the\nshape you would get.\nThe pyramid of biomass in sea is generally inverted because the\nbiomass of fishes far exceeds that of phytoplankton. Isn’t that a paradox?\nHow would you explain this?\nPyramid of energy is always upright, can never be inverted,  because\nwhen energy flows from a particular trophic level to the next trophic level,\nsome energy is always lost as heat at each step. Each bar in the energy\npyramid indicates the amount of energy present at each trophic level in a\ngiven time or annually per unit area."
    },
    {
      "page": 10,
      "text": "214\nBIOLOGY\nSUMMARY\nAn ecosystem is a structural and functional unit of nature and it\ncomprises abiotic and biotic components. Abiotic components are\ninorganic materials- air, water and soil, whereas biotic components\nare producers, consumers and decomposers. Each ecosystem has\ncharacteristic physical structure resulting from interaction amongst\nabiotic and biotic components. Species composition and stratification\nare the two main structural features of an ecosystem. Based on source\nof nutrition every organism occupies a place in an ecosystem.\nProductivity, decomposition, energy flow, and nutrient cycling are\nthe four important components of an ecosystem. Primary productivity\nis the rate of capture of solar energy or biomass production of the\nproducers. It is divided into two types: gross primary productivity (GPP)\nand net primary productivity (NPP). Rate of capture of solar energy or\ntotal production of organic matter is called as GPP. NPP is the remaining\nbiomass or the energy left after utilisation of producers. Secondary\nproductivity is the rate of assimilation of food energy by the consumers.\nIn decomposition, complex organic compounds of detritus are converted\nto carbon dioxide, water and inorganic nutrients by the decomposers.\nDecomposition involves three processes, namely fragmentation of\ndetritus, leaching and catabolism.\nEnergy flow is unidirectional. First, plants capture solar energy\nand then, food is transferred from the producers to decomposers.\nOrganisms of different trophic levels in nature are connected to each\nother for food or energy relationship forming a food chain. The storage\nand movement of nutrient elements through the various components\nof the ecosystem is called nutrient cycling; nutrients are repeatedly\nused through this process. Nutrient cycling is of two types—gaseous\nand sedimentary. Atmosphere or hydrosphere is the reservoir for the\ngaseous type of cycle (carbon), whereas Earth’s crust is the reservoir\nfor sedimentary type (phosphorus). Products of ecosystem processes\nare named as ecosystem services, e.g., purification of air and water by\nforests.\nEXERCISES\n1.\nFill in the blanks.\n(a) Plants are called as_________because they fix carbon dioxide.\n(b) In an ecosystem dominated by trees, the pyramid (of numbers)\nis_________type.\nHowever, there are certain limitations of ecological pyramids such as\nit does not take into account the same species belonging to two or more\ntrophic levels. It assumes a simple food chain, something that almost\nnever exists in nature; it does not accommodate a food web. Moreover,\nsaprophytes are not given any place in ecological pyramids even though\nthey play a vital role in the ecosystem."
    },
    {
      "page": 11,
      "text": "215\nECOSYSTEM\n(c) In aquatic ecosystems, the limiting factor for the productivity\nis_________.\n(d) Common detritivores in our ecosystem are_________.\n(e) The major reservoir of carbon on earth is_________.\n2.\nWhich one of the following has the largest population in a food chain?\n(a) Producers\n(b) Primary consumers\n(c) Secondary consumers\n(d) Decomposers\n3.\nThe second trophic level in a lake is\n(a)  Phytoplankton\n(b) Zooplankton\n(c) Benthos\n(d) Fishes\n4.\nSecondary producers are\n(a) Herbivores\n(b) Producers\n(c) Carnivores\n(d) None of the above\n5.\nWhat is the percentage of photosynthetically active radiation (PAR) in\nthe incident solar radiation?\n(a) 100%\n(b) 50 %\n(c) 1-5%\n(d) 2-10%\n6.\nDistinguish between\n(a) Grazing food chain and detritus food chain\n(b) Production and decomposition\n(c) Upright and inverted pyramid\n(d) Food chain and Food web\n(e) Litter and detritus\n(f)\nPrimary and secondary productivity\n7.\nDescribe the components of an ecosystem.\n8.\nDefine ecological pyramids and describe with examples, pyramids of\nnumber and biomass.\n9.\nWhat is primary productivity? Give brief description of factors that affect\nprimary productivity.\n10.  Define decomposition and describe the processes and products of\ndecomposition.\n11.\nGive an account of energy flow in an ecosystem."
    }
  ]
}